{"algorithm":"Kruskal","graphId":"18","edges":[{"from":"DY","to":"F","weight":1},{"from":"DX","to":"JO","weight":1},{"from":"BR","to":"GU","weight":1},{"from":"GM","to":"ME","weight":1},{"from":"JN","to":"MI","weight":1},{"from":"ID","to":"LS","weight":1},{"from":"GC","to":"IJ","weight":1},{"from":"ES","to":"JM","weight":1},{"from":"CR","to":"EY","weight":1},{"from":"IM","to":"IS","weight":1},{"from":"BG","to":"HJ","weight":1},{"from":"FA","to":"HB","weight":1},{"from":"BQ","to":"IE","weight":1},{"from":"EA","to":"JZ","weight":1},{"from":"CP","to":"HM","weight":1},{"from":"GP","to":"HI","weight":1},{"from":"JO","to":"KX","weight":1},{"from":"AW","to":"KD","weight":1},{"from":"IM","to":"LO","weight":1},{"from":"EX","to":"GU","weight":1},{"from":"JN","to":"JP","weight":1},{"from":"JE","to":"LO","weight":1},{"from":"ET","to":"LY","weight":1},{"from":"GJ","to":"IJ","weight":1},{"from":"KG","to":"LP","weight":1},{"from":"HG","to":"IC","weight":1},{"from":"BJ","to":"KP","weight":1},{"from":"JI","to":"JS","weight":1},{"from":"AR","to":"KU","weight":1},{"from":"HM","to":"JJ","weight":1},{"from":"AA","to":"FX","weight":1},{"from":"DD","to":"LT","weight":1},{"from":"GJ","to":"IZ","weight":1},{"from":"DW","to":"ET","weight":1},{"from":"CD","to":"KJ","weight":1},{"from":"DN","to":"DT","weight":1},{"from":"AA","to":"GZ","weight":1},{"from":"EY","to":"LC","weight":1},{"from":"F","to":"KJ","weight":1},{"from":"BW","to":"LM","weight":1},{"from":"JY","to":"KF","weight":1},{"from":"HF","to":"LG","weight":1},{"from":"F","to":"LY","weight":1},{"from":"KV","to":"LQ","weight":1},{"from":"ER","to":"LX","weight":1},{"from":"BZ","to":"GN","weight":1},{"from":"DS","to":"DY","weight":1},{"from":"FC","to":"GN","weight":1},{"from":"CI","to":"J","weight":1},{"from":"AA","to":"LZ","weight":1},{"from":"HL","to":"KT","weight":2},{"from":"BM","to":"FA","weight":2},{"from":"FM","to":"GJ","weight":2},{"from":"AB","to":"LH","weight":2},{"from":"AP","to":"BD","weight":2},{"from":"FP","to":"W","weight":2},{"from":"IO","to":"JX","weight":2},{"from":"LK","to":"LU","weight":2},{"from":"JL","to":"LT","weight":2},{"from":"FY","to":"IK","weight":2},{"from":"C","to":"E","weight":2},{"from":"CH","to":"CJ","weight":2},{"from":"DF","to":"EW","weight":2},{"from":"GM","to":"HW","weight":2},{"from":"EB","to":"KE","weight":2},{"from":"AT","to":"EL","weight":2},{"from":"AC","to":"HY","weight":2},{"from":"BL","to":"DN","weight":2},{"from":"DC","to":"N","weight":2},{"from":"AP","to":"JN","weight":2},{"from":"EL","to":"G","weight":2},{"from":"AV","to":"LN","weight":2},{"from":"E","to":"LP","weight":2},{"from":"EG","to":"HD","weight":2},{"from":"DY","to":"HO","weight":2},{"from":"IQ","to":"JZ","weight":2},{"from":"HR","to":"JG","weight":2},{"from":"GU","to":"KV","weight":2},{"from":"EN","to":"IG","weight":2},{"from":"CC","to":"KZ","weight":2},{"from":"BI","to":"EU","weight":2},{"from":"CC","to":"CF","weight":2},{"from":"AP","to":"LO","weight":2},{"from":"AY","to":"FD","weight":2},{"from":"AR","to":"CN","weight":2},{"from":"GJ","to":"II","weight":2},{"from":"IN","to":"JU","weight":2},{"from":"HB","to":"IV","weight":2},{"from":"IA","to":"L","weight":2},{"from":"HQ","to":"HT","weight":2},{"from":"BR","to":"HF","weight":2},{"from":"CI","to":"MC","weight":2},{"from":"HL","to":"Z","weight":2},{"from":"CC","to":"HL","weight":2},{"from":"CW","to":"GV","weight":2},{"from":"BS","to":"E","weight":2},{"from":"DF","to":"JX","weight":2},{"from":"FE","to":"LI","weight":2},{"from":"BQ","to":"DZ","weight":2},{"from":"GB","to":"O","weight":2},{"from":"FC","to":"KG","weight":2},{"from":"HM","to":"KE","weight":2},{"from":"KX","to":"ML","weight":2},{"from":"CZ","to":"KO","weight":2},{"from":"HH","to":"KA","weight":2},{"from":"BN","to":"HP","weight":2},{"from":"BA","to":"IT","weight":2},{"from":"DI","to":"EI","weight":3},{"from":"BZ","to":"Q","weight":3},{"from":"CJ","to":"EH","weight":3},{"from":"DH","to":"DI","weight":3},{"from":"BA","to":"DU","weight":3},{"from":"AT","to":"JR","weight":3},{"from":"AR","to":"DG","weight":3},{"from":"GW","to":"IV","weight":3},{"from":"MC","to":"Q","weight":3},{"from":"KS","to":"MM","weight":3},{"from":"CZ","to":"DJ","weight":3},{"from":"HK","to":"LD","weight":3},{"from":"KA","to":"LE","weight":3},{"from":"LF","to":"LS","weight":3},{"from":"IA","to":"LB","weight":3},{"from":"EV","to":"U","weight":3},{"from":"CZ","to":"FK","weight":3},{"from":"KL","to":"MA","weight":3},{"from":"BV","to":"CM","weight":3},{"from":"G","to":"KP","weight":3},{"from":"FX","to":"JG","weight":3},{"from":"D","to":"GN","weight":3},{"from":"GX","to":"HL","weight":3},{"from":"BR","to":"DT","weight":3},{"from":"BG","to":"LO","weight":3},{"from":"JH","to":"KR","weight":3},{"from":"FU","to":"LL","weight":3},{"from":"E","to":"IF","weight":3},{"from":"AO","to":"ES","weight":3},{"from":"IU","to":"JF","weight":3},{"from":"IA","to":"R","weight":3},{"from":"AC","to":"ML","weight":3},{"from":"B","to":"FN","weight":3},{"from":"GO","to":"N","weight":3},{"from":"DP","to":"EA","weight":3},{"from":"KN","to":"R","weight":3},{"from":"EZ","to":"IW","weight":3},{"from":"EO","to":"KX","weight":3},{"from":"HI","to":"IQ","weight":3},{"from":"CO","to":"LC","weight":3},{"from":"FY","to":"HO","weight":3},{"from":"CS","to":"EW","weight":3},{"from":"IT","to":"N","weight":3},{"from":"KL","to":"LC","weight":3},{"from":"HT","to":"ML","weight":3},{"from":"CO","to":"DW","weight":3},{"from":"DU","to":"Y","weight":3},{"from":"DV","to":"GK","weight":3},{"from":"EF","to":"FF","weight":3},{"from":"EV","to":"KH","weight":3},{"from":"GL","to":"JL","weight":3},{"from":"CC","to":"JH","weight":3},{"from":"FW","to":"JX","weight":3},{"from":"GQ","to":"LY","weight":3},{"from":"HX","to":"LP","weight":4},{"from":"GW","to":"LJ","weight":4},{"from":"CB","to":"KO","weight":4},{"from":"A","to":"ET","weight":4},{"from":"O","to":"T","weight":4},{"from":"EO","to":"FU","weight":4},{"from":"AT","to":"FT","weight":4},{"from":"DS","to":"GM","weight":4},{"from":"FO","to":"FP","weight":4},{"from":"AS","to":"JZ","weight":4},{"from":"AE","to":"E","weight":4},{"from":"HQ","to":"LS","weight":4},{"from":"GV","to":"LQ","weight":4},{"from":"CQ","to":"IA","weight":4},{"from":"BF","to":"DE","weight":4},{"from":"BP","to":"LU","weight":4},{"from":"EP","to":"S","weight":4},{"from":"BO","to":"P","weight":4},{"from":"HB","to":"JQ","weight":4},{"from":"CQ","to":"JV","weight":4},{"from":"BY","to":"CU","weight":4},{"from":"CR","to":"KE","weight":4},{"from":"FK","to":"HQ","weight":4},{"from":"AT","to":"EE","weight":4},{"from":"EL","to":"HU","weight":4},{"from":"CF","to":"MI","weight":4},{"from":"DE","to":"MM","weight":4},{"from":"D","to":"HC","weight":4},{"from":"CV","to":"FU","weight":4},{"from":"BJ","to":"KF","weight":4},{"from":"CN","to":"EQ","weight":4},{"from":"IC","to":"JF","weight":4},{"from":"F","to":"LD","weight":4},{"from":"AU","to":"FY","weight":4},{"from":"BY","to":"IZ","weight":4},{"from":"CJ","to":"EL","weight":4},{"from":"HM","to":"L","weight":4},{"from":"CF","to":"DB","weight":4},{"from":"FW","to":"KI","weight":4},{"from":"DA","to":"ES","weight":4},{"from":"AI","to":"CL","weight":4},{"from":"CE","to":"IV","weight":4},{"from":"BH","to":"GI","weight":4},{"from":"CG","to":"DX","weight":4},{"from":"GP","to":"JC","weight":4},{"from":"DI","to":"G","weight":5},{"from":"DJ","to":"HO","weight":5},{"from":"FM","to":"MB","weight":5},{"from":"DA","to":"KD","weight":5},{"from":"EW","to":"L","weight":5},{"from":"EW","to":"LT","weight":5},{"from":"DA","to":"P","weight":5},{"from":"IF","to":"KB","weight":5},{"from":"KY","to":"MM","weight":5},{"from":"DW","to":"MF","weight":5},{"from":"HD","to":"HY","weight":5},{"from":"AC","to":"I","weight":5},{"from":"BE","to":"CF","weight":5},{"from":"FY","to":"IW","weight":5},{"from":"CW","to":"IG","weight":5},{"from":"DG","to":"FH","weight":5},{"from":"DE","to":"MH","weight":5},{"from":"HM","to":"MI","weight":5},{"from":"AB","to":"IQ","weight":5},{"from":"GE","to":"KA","weight":5},{"from":"KM","to":"LV","weight":5},{"from":"BL","to":"GK","weight":5},{"from":"GU","to":"HL","weight":5},{"from":"KS","to":"MF","weight":5},{"from":"DB","to":"FF","weight":5},{"from":"AQ","to":"JL","weight":5},{"from":"ES","to":"FA","weight":5},{"from":"AW","to":"MF","weight":5},{"from":"EZ","to":"FI","weight":5},{"from":"CO","to":"S","weight":5},{"from":"A","to":"AI","weight":5},{"from":"IG","to":"JK","weight":5},{"from":"IJ","to":"Z","weight":5},{"from":"HC","to":"IJ","weight":5},{"from":"BN","to":"GL","weight":5},{"from":"LZ","to":"V","weight":5},{"from":"ES","to":"LA","weight":5},{"from":"HR","to":"Z","weight":5},{"from":"KO","to":"X","weight":5},{"from":"ER","to":"KR","weight":5},{"from":"AV","to":"IR","weight":5},{"from":"AX","to":"JD","weight":5},{"from":"CY","to":"EE","weight":5},{"from":"HU","to":"JD","weight":5},{"from":"IT","to":"JU","weight":5},{"from":"DO","to":"G","weight":5},{"from":"DU","to":"FK","weight":5},{"from":"GB","to":"ML","weight":5},{"from":"D","to":"LU","weight":5},{"from":"LE","to":"U","weight":5},{"from":"AY","to":"LO","weight":5},{"from":"BG","to":"DO","weight":6},{"from":"KM","to":"LQ","weight":6},{"from":"AZ","to":"DV","weight":6},{"from":"JW","to":"KM","weight":6},{"from":"KQ","to":"KX","weight":6},{"from":"CK","to":"LW","weight":6},{"from":"GG","to":"JJ","weight":6},{"from":"FB","to":"IT","weight":6},{"from":"BM","to":"IB","weight":6},{"from":"EU","to":"FF","weight":6},{"from":"EA","to":"IK","weight":6},{"from":"DS","to":"FP","weight":6},{"from":"GF","to":"HJ","weight":6},{"from":"BU","to":"IB","weight":6},{"from":"FN","to":"JV","weight":6},{"from":"CK","to":"IM","weight":6},{"from":"AK","to":"KK","weight":6},{"from":"CG","to":"HZ","weight":6},{"from":"FE","to":"HU","weight":6},{"from":"BG","to":"GR","weight":6},{"from":"CM","to":"IW","weight":6},{"from":"HN","to":"KO","weight":6},{"from":"AB","to":"DK","weight":6},{"from":"GS","to":"O","weight":6},{"from":"EJ","to":"V","weight":6},{"from":"FM","to":"LR","weight":6},{"from":"CX","to":"KP","weight":7},{"from":"AK","to":"JU","weight":7},{"from":"GT","to":"KU","weight":7},{"from":"EZ","to":"IR","weight":7},{"from":"FV","to":"JE","weight":7},{"from":"IK","to":"KU","weight":7},{"from":"JY","to":"KA","weight":7},{"from":"BX","to":"EM","weight":7},{"from":"AF","to":"LJ","weight":7},{"from":"BW","to":"HS","weight":7},{"from":"DK","to":"HG","weight":7},{"from":"EK","to":"HA","weight":7},{"from":"LC","to":"MK","weight":7},{"from":"DN","to":"IH","weight":7},{"from":"FS","to":"FW","weight":7},{"from":"FG","to":"IA","weight":7},{"from":"FV","to":"JB","weight":7},{"from":"JA","to":"JG","weight":7},{"from":"IL","to":"W","weight":7},{"from":"GW","to":"HS","weight":7},{"from":"AJ","to":"HN","weight":7},{"from":"EK","to":"GU","weight":7},{"from":"AL","to":"KP","weight":8},{"from":"BX","to":"CB","weight":8},{"from":"DJ","to":"DR","weight":8},{"from":"BH","to":"BY","weight":8},{"from":"DO","to":"MG","weight":8},{"from":"JS","to":"KK","weight":8},{"from":"EV","to":"FQ","weight":8},{"from":"AH","to":"CJ","weight":8},{"from":"BO","to":"IY","weight":8},{"from":"AN","to":"DN","weight":8},{"from":"CA","to":"FJ","weight":9},{"from":"BK","to":"GH","weight":9},{"from":"AT","to":"HV","weight":9},{"from":"GY","to":"MI","weight":9},{"from":"DR","to":"KW","weight":9},{"from":"BK","to":"KB","weight":9},{"from":"HA","to":"MD","weight":9},{"from":"AM","to":"JX","weight":9},{"from":"DL","to":"GS","weight":9},{"from":"BQ","to":"FT","weight":9},{"from":"AS","to":"FZ","weight":9},{"from":"LX","to":"M","weight":10},{"from":"AU","to":"CA","weight":10},{"from":"CD","to":"K","weight":10},{"from":"AP","to":"BB","weight":10},{"from":"BS","to":"CT","weight":11},{"from":"FL","to":"KK","weight":11},{"from":"ED","to":"FJ","weight":11},{"from":"AP","to":"HE","weight":11},{"from":"GD","to":"JT","weight":11},{"from":"CS","to":"DQ","weight":11},{"from":"AX","to":"GD","weight":11},{"from":"JE","to":"MJ","weight":12},{"from":"BC","to":"FA","weight":12},{"from":"AG","to":"LI","weight":12},{"from":"GA","to":"JN","weight":12},{"from":"IP","to":"LU","weight":13},{"from":"AA","to":"AD","weight":14},{"from":"IX","to":"JQ","weight":14},{"from":"EC","to":"IO","weight":14},{"from":"AQ","to":"KC","weight":16},{"from":"BT","to":"HH","weight":17},{"from":"FR","to":"IQ","weight":17},{"from":"EF","to":"H","weight":18}],"totalCost":1538.0,"executionTimeMs":0.627208,"operationsCount":2457}