{"algorithm":"Prim","graphId":"15","edges":[{"from":"A","to":"FW","weight":5},{"from":"FW","to":"FB","weight":2},{"from":"FB","to":"CO","weight":4},{"from":"FW","to":"CV","weight":5},{"from":"FW","to":"BM","weight":5},{"from":"BM","to":"GI","weight":1},{"from":"GI","to":"CY","weight":2},{"from":"CY","to":"BR","weight":2},{"from":"BR","to":"GQ","weight":3},{"from":"BR","to":"AK","weight":3},{"from":"AK","to":"I","weight":1},{"from":"I","to":"GM","weight":2},{"from":"I","to":"BT","weight":3},{"from":"I","to":"HI","weight":4},{"from":"GI","to":"BS","weight":4},{"from":"GM","to":"E","weight":4},{"from":"E","to":"FM","weight":1},{"from":"GM","to":"EN","weight":4},{"from":"CY","to":"DT","weight":4},{"from":"EN","to":"BJ","weight":4},{"from":"BJ","to":"CR","weight":1},{"from":"BJ","to":"AI","weight":2},{"from":"HI","to":"GW","weight":4},{"from":"GW","to":"ED","weight":2},{"from":"GW","to":"BC","weight":3},{"from":"BC","to":"FK","weight":1},{"from":"FK","to":"C","weight":1},{"from":"ED","to":"AL","weight":3},{"from":"FK","to":"EX","weight":3},{"from":"FK","to":"CL","weight":3},{"from":"C","to":"DW","weight":3},{"from":"DW","to":"X","weight":3},{"from":"BJ","to":"GU","weight":4},{"from":"ED","to":"BY","weight":4},{"from":"BY","to":"AW","weight":3},{"from":"AW","to":"EL","weight":2},{"from":"ED","to":"FX","weight":4},{"from":"FX","to":"BF","weight":1},{"from":"FX","to":"CT","weight":3},{"from":"CT","to":"FV","weight":3},{"from":"FV","to":"DF","weight":2},{"from":"DF","to":"G","weight":1},{"from":"CL","to":"HQ","weight":4},{"from":"BF","to":"AM","weight":4},{"from":"G","to":"BQ","weight":4},{"from":"DW","to":"HM","weight":5},{"from":"HM","to":"AQ","weight":1},{"from":"AQ","to":"DY","weight":1},{"from":"AQ","to":"EV","weight":2},{"from":"EV","to":"AN","weight":3},{"from":"AN","to":"EF","weight":2},{"from":"EF","to":"HD","weight":1},{"from":"HD","to":"ET","weight":1},{"from":"HM","to":"GE","weight":4},{"from":"EF","to":"CS","weight":4},{"from":"CS","to":"BP","weight":1},{"from":"CS","to":"D","weight":4},{"from":"D","to":"GV","weight":1},{"from":"GV","to":"R","weight":3},{"from":"R","to":"HE","weight":4},{"from":"HE","to":"BN","weight":2},{"from":"GW","to":"GK","weight":5},{"from":"GK","to":"EB","weight":1},{"from":"EB","to":"FF","weight":1},{"from":"GK","to":"HJ","weight":2},{"from":"GK","to":"W","weight":3},{"from":"W","to":"GO","weight":3},{"from":"FB","to":"FS","weight":5},{"from":"AK","to":"ES","weight":5},{"from":"GO","to":"HS","weight":5},{"from":"HS","to":"EG","weight":3},{"from":"HM","to":"EQ","weight":5},{"from":"HS","to":"GZ","weight":5},{"from":"E","to":"CM","weight":5},{"from":"GZ","to":"GH","weight":5},{"from":"GH","to":"GY","weight":3},{"from":"GZ","to":"FU","weight":5},{"from":"AI","to":"FC","weight":5},{"from":"EF","to":"FI","weight":5},{"from":"C","to":"AY","weight":5},{"from":"GM","to":"N","weight":5},{"from":"BJ","to":"O","weight":5},{"from":"O","to":"CG","weight":1},{"from":"CG","to":"B","weight":1},{"from":"B","to":"Z","weight":1},{"from":"O","to":"HT","weight":2},{"from":"DW","to":"GB","weight":5},{"from":"BP","to":"GG","weight":5},{"from":"GG","to":"HU","weight":1},{"from":"D","to":"HN","weight":5},{"from":"HN","to":"BL","weight":2},{"from":"BL","to":"DD","weight":1},{"from":"BL","to":"BO","weight":3},{"from":"DF","to":"Y","weight":5},{"from":"Y","to":"DQ","weight":1},{"from":"DQ","to":"GJ","weight":4},{"from":"DQ","to":"GL","weight":4},{"from":"GL","to":"HV","weight":3},{"from":"BO","to":"DM","weight":5},{"from":"GM","to":"ER","weight":5},{"from":"FF","to":"DC","weight":6},{"from":"DC","to":"DG","weight":2},{"from":"DC","to":"CD","weight":2},{"from":"DG","to":"CP","weight":2},{"from":"CP","to":"EM","weight":2},{"from":"CD","to":"AA","weight":3},{"from":"EM","to":"CU","weight":5},{"from":"DG","to":"FL","weight":6},{"from":"FL","to":"AV","weight":1},{"from":"FL","to":"BK","weight":5},{"from":"BK","to":"FY","weight":3},{"from":"BK","to":"EI","weight":4},{"from":"FY","to":"CA","weight":5},{"from":"CA","to":"L","weight":1},{"from":"L","to":"BH","weight":1},{"from":"ER","to":"FA","weight":6},{"from":"HV","to":"F","weight":6},{"from":"F","to":"AX","weight":1},{"from":"AX","to":"AJ","weight":2},{"from":"F","to":"FT","weight":3},{"from":"AJ","to":"GP","weight":3},{"from":"GP","to":"GN","weight":2},{"from":"GN","to":"EO","weight":3},{"from":"EO","to":"AD","weight":2},{"from":"AD","to":"BI","weight":2},{"from":"EO","to":"AP","weight":3},{"from":"BI","to":"DB","weight":3},{"from":"DB","to":"EK","weight":1},{"from":"AJ","to":"AS","weight":4},{"from":"AS","to":"BA","weight":1},{"from":"BI","to":"EZ","weight":4},{"from":"EZ","to":"HA","weight":3},{"from":"BI","to":"CI","weight":4},{"from":"CI","to":"AB","weight":2},{"from":"AD","to":"Q","weight":5},{"from":"Q","to":"DR","weight":1},{"from":"Q","to":"FQ","weight":5},{"from":"CL","to":"DE","weight":6},{"from":"DE","to":"HR","weight":5},{"from":"HR","to":"AU","weight":1},{"from":"AU","to":"GR","weight":1},{"from":"GR","to":"AF","weight":3},{"from":"AF","to":"DI","weight":2},{"from":"HR","to":"HF","weight":4},{"from":"HF","to":"HL","weight":1},{"from":"HF","to":"AE","weight":2},{"from":"AE","to":"FD","weight":1},{"from":"HF","to":"CW","weight":5},{"from":"CW","to":"GF","weight":1},{"from":"BH","to":"GA","weight":6},{"from":"ER","to":"HP","weight":6},{"from":"HP","to":"HG","weight":1},{"from":"HP","to":"EJ","weight":2},{"from":"HP","to":"CE","weight":3},{"from":"GN","to":"AZ","weight":6},{"from":"AZ","to":"DV","weight":5},{"from":"HD","to":"DK","weight":6},{"from":"DK","to":"BB","weight":2},{"from":"DK","to":"EY","weight":2},{"from":"EL","to":"HC","weight":6},{"from":"CI","to":"CF","weight":6},{"from":"EK","to":"K","weight":6},{"from":"DE","to":"BZ","weight":6},{"from":"GA","to":"CZ","weight":6},{"from":"BZ","to":"DA","weight":6},{"from":"ES","to":"FZ","weight":7},{"from":"GY","to":"DS","weight":7},{"from":"DS","to":"EE","weight":4},{"from":"EE","to":"J","weight":4},{"from":"DS","to":"EP","weight":5},{"from":"EN","to":"DX","weight":7},{"from":"DX","to":"DL","weight":2},{"from":"DL","to":"T","weight":4},{"from":"J","to":"EH","weight":7},{"from":"AN","to":"DJ","weight":7},{"from":"DJ","to":"AT","weight":1},{"from":"DJ","to":"AC","weight":4},{"from":"DE","to":"CN","weight":7},{"from":"CN","to":"DZ","weight":3},{"from":"AU","to":"EW","weight":7},{"from":"EW","to":"CK","weight":4},{"from":"CK","to":"AH","weight":6},{"from":"DE","to":"H","weight":7},{"from":"H","to":"BX","weight":1},{"from":"BX","to":"HO","weight":6},{"from":"AJ","to":"EA","weight":7},{"from":"EA","to":"HH","weight":4},{"from":"HH","to":"FE","weight":5},{"from":"AW","to":"GD","weight":7},{"from":"GD","to":"DH","weight":3},{"from":"EX","to":"BV","weight":7},{"from":"HE","to":"GS","weight":7},{"from":"DV","to":"P","weight":8},{"from":"AM","to":"FR","weight":8},{"from":"AM","to":"CB","weight":8},{"from":"CW","to":"FG","weight":8},{"from":"DE","to":"BE","weight":8},{"from":"BE","to":"U","weight":1},{"from":"AY","to":"HK","weight":9},{"from":"GB","to":"AO","weight":9},{"from":"GG","to":"HW","weight":9},{"from":"HA","to":"CQ","weight":9},{"from":"GS","to":"GT","weight":9},{"from":"GT","to":"CX","weight":5},{"from":"CX","to":"DN","weight":9},{"from":"DN","to":"EC","weight":9},{"from":"EX","to":"BG","weight":9},{"from":"X","to":"DP","weight":10},{"from":"DP","to":"FJ","weight":4},{"from":"FJ","to":"S","weight":9},{"from":"EJ","to":"DO","weight":10},{"from":"DO","to":"GC","weight":5},{"from":"L","to":"EU","weight":10},{"from":"DB","to":"BD","weight":10},{"from":"GO","to":"HB","weight":11},{"from":"DT","to":"V","weight":11},{"from":"V","to":"AG","weight":6},{"from":"EC","to":"FN","weight":12},{"from":"CF","to":"FH","weight":12},{"from":"HA","to":"BU","weight":12},{"from":"FZ","to":"CC","weight":12},{"from":"Q","to":"DU","weight":12},{"from":"DU","to":"CH","weight":9},{"from":"HD","to":"CJ","weight":12},{"from":"P","to":"FO","weight":13},{"from":"AY","to":"GX","weight":13},{"from":"BN","to":"FP","weight":14},{"from":"FL","to":"M","weight":15},{"from":"GY","to":"AR","weight":18},{"from":"FN","to":"BW","weight":18}],"totalCost":1047.0,"executionTimeMs":0.652834,"operationsCount":1543}